{
  "next": null,
  "previous": null,
  "total": 13,
  "count": 13,
  "results": [
    {
      "index": 0,
      "lang": "en",
      "para_id": "12668.20451",
      "pub_code": "SDAEnc",
      "pub_name": "SDA Encyclopedia",
      "refcode_long": "SDA Encyclopedia, p. .0 (General Conference of SDA)",
      "refcode_short": "SDAEnc .0",
      "pub_year": "1966",
      "snippet": "",
      "weight": 1,
      "group": "bible",
      "action_required": "purchased"
    },
    {
      "index": 1,
      "lang": "en",
      "para_id": "12513.17528",
      "pub_code": "4SDABC",
      "pub_name": "SDA Bible Commentary, vol. 4",
      "refcode_long": "SDA Bible Commentary, vol. 4, p. 879.3 (Francis Nichol-GCSDA)",
      "refcode_short": "4SDABC 879.3",
      "pub_year": "1955",
      "snippet": "",
      "weight": 0.65,
      "group": "bible",
      "action_required": "purchased"
    },
    {
      "index": 2,
      "lang": "en",
      "para_id": "1322.26",
      "pub_code": "MWSV2",
      "pub_name": "Miller’s Works, vol. 2. Supplement",
      "refcode_long": "Miller’s Works, vol. 2. Supplement",
      "refcode_short": "MWSV2",
      "pub_year": "1842",
      "snippet": "1798. A. D.]to] 1843. A. D.][ ,<mark>Rev</mark>. Chap.<mark>10</mark>. Opening of the <mark>Little Book</mark>. 45 years to End",
      "weight": 0.44,
      "group": "apl"
    },
    {
      "index": 3,
      "lang": "en",
      "para_id": "12517.18480",
      "pub_code": "7SDABC",
      "pub_name": "SDA Bible Commentary, vol. 7",
      "refcode_long": "SDA Bible Commentary, vol. 7, p. 797.9 (Francis Nichol-GCSDA)",
      "refcode_short": "7SDABC 797.9",
      "pub_year": "1957",
      "snippet": "",
      "weight": 0.43,
      "group": "bible",
      "action_required": "purchased"
    },
    {
      "index": 4,
      "lang": "en",
      "para_id": "12517.18531",
      "pub_code": "7SDABC",
      "pub_name": "SDA Bible Commentary, vol. 7",
      "refcode_long": "SDA Bible Commentary, vol. 7, p. 798.19 (Francis Nichol-GCSDA)",
      "refcode_short": "7SDABC 798.19",
      "pub_year": "1957",
      "snippet": "",
      "weight": 0.42,
      "group": "bible",
      "action_required": "purchased"
    },
    {
      "index": 5,
      "lang": "en",
      "para_id": "949.2220",
      "pub_code": "FSDA",
      "pub_name": "Foundations of the Seventh-day Adventist Message and Mission",
      "refcode_long": "Foundations of the Seventh-day Adventist Message and Mission, p. 346 (Pieter Gerard Damsteegt)",
      "refcode_short": "FSDA 346",
      "pub_year": "1977",
      "snippet": "… , 26 <mark>Little book</mark> of <mark>Rev. 10</mark>; 21, 105 <mark>Little</mark> horn of Daniel 8; 30, 32, 33, 57, 59-61, 65-68, 73-75, 77, 252 Dan. 7; 23-25, 32, 59, 60, 65, 68, 70, 73-75, 137, 196, 252 Loud Cry, 219-21, 233, 241, 275, 280, 285 …",
      "weight": 0.34,
      "group": "apl"
    },
    {
      "index": 6,
      "lang": "en",
      "para_id": "1658.532",
      "pub_code": "HST",
      "pub_name": "Signs of the Times and Expositor of Prophecy [Himes], vol. 2",
      "refcode_long": "Signs of the Times and Expositor of Prophecy [Himes], vol. 2 May 1,  1841, page 20 paragraph 15",
      "refcode_short": "HST May 1,  1841, page 20.15",
      "pub_year": "1841",
      "snippet": "… . D. <mark>Rev</mark>. Chap. <mark>10</mark>. Opening of the <mark>Little Book</mark>. 45 years to the End. Note. The reader will find the different prophecies referred to in this Chart fully explained in …",
      "weight": 0.29,
      "group": "apl"
    },
    {
      "index": 7,
      "lang": "en",
      "para_id": "14341.45392",
      "pub_code": "NET",
      "pub_name": "New English Translation",
      "refcode_long": "New English Translation — Hosea 11:4",
      "refcode_short": "NET — Hosea 11:4",
      "pub_year": "",
      "snippet": "",
      "weight": 0.06,
      "group": "bible",
      "action_required": "authenticated"
    },
    {
      "index": 8,
      "lang": "en",
      "para_id": "973.144",
      "pub_code": "BP2",
      "pub_name": "[Bates’ Pamphlet #2] Second Advent Way Marks and High Heaps",
      "refcode_long": "[Bates’ Pamphlet #2] Second Advent Way Marks and High Heaps, p. 75.1 (Joseph Bates)",
      "refcode_short": "BP2 75.1",
      "pub_year": "1847",
      "snippet": "… a <mark>little</mark> strength, and hast kept my WORD, and hast not denied my name.” Revelation 3:4, 7, 8. The 9th to 13th v. show what will follow, viz. the confession of them that lie …",
      "weight": 0.05,
      "group": "apl"
    },
    {
      "index": 9,
      "lang": "en",
      "para_id": "11161.18101",
      "pub_code": "TopIndex",
      "pub_name": "EGW Index, vols. 1-4 (Topical Index)",
      "refcode_long": "EGW Index, vols. 1-4 (Topical Index), Book, Books.198",
      "refcode_short": "TopIndex .Book, Books.198",
      "pub_year": "1962",
      "snippet": "<mark>Book, Books, little</mark>, of <mark>Rev. 10</mark>:1, 8-<mark>10</mark> 7BC 971",
      "weight": 0.04,
      "group": "reference"
    },
    {
      "index": 10,
      "lang": "en",
      "para_id": "12667.442",
      "pub_code": "1EGWLM",
      "pub_name": "The Ellen G. White Letters and Manuscripts: Volume 1",
      "refcode_long": "The Ellen G. White Letters and Manuscripts: Volume 1, p. 85.4 (Ellen Gould White)",
      "refcode_short": "1EGWLM 85.4",
      "pub_year": "2014",
      "snippet": "… the <mark>little</mark> ones climb, or if they chose use their <mark>little</mark> wings and fly to the top of the mountains, and pluck the never fading flowers. There were all kinds of …",
      "weight": 0.04,
      "group": "egwwritings"
    },
    {
      "index": 11,
      "lang": "en",
      "para_id": "1679.8367",
      "pub_code": "ARSH",
      "pub_name": "Advent Review, and Sabbath Herald, vol. 24",
      "refcode_long": "Advent Review, and Sabbath Herald, vol. 24 November 22,  1864, page 207",
      "refcode_short": "ARSH November 22,  1864, page 207",
      "pub_year": "1864",
      "snippet": "… 101 <mark>Books</mark> on Present Truth 106 <mark>Book</mark> on Slavery 136 Bringing a Man to Prayer Meeting 150 Be of One Mind 175 Cheerfulness 35 Counsel from Paul 66 Christian Consistency …",
      "weight": 0.03,
      "group": "apl"
    },
    {
      "index": 12,
      "lang": "en",
      "para_id": "1648.555",
      "pub_code": "HST",
      "pub_name": "The Advent Herald, and Signs of the Times Reporter [Himes], vol. 8",
      "refcode_long": "The Advent Herald, and Signs of the Times Reporter [Himes], vol. 8 August 14,  1844, page 16 paragraph 41",
      "refcode_short": "HST August 14,  1844, page 16.41",
      "pub_year": "1844",
      "snippet": "… ; J <mark>Little</mark> by pm $1 pd to 153 v 7; Wm Hill by pm $2 pd to end v 6; S W Dow by pm $1 pd to 206 v 9; <mark>Rev</mark> O. Gregg by pm $3 pd to end v 8; Dr Austin Flint by pm $1 pd to end v 8; L F Allen by pm $1 pd to …",
      "weight": 0.01,
      "group": "apl"
    }
  ]
}
