[
  {
    "paraId": "12861.2516",
    "refcodeShort": "DAR 483.2",
    "content": "“It was to ‘the fire and the smoke and the sulphur,’ to the artillery and firearms of Mahomet, that the killing of the third part of men, <em>i</em>. <em>e</em>., the capture of Constantinople, and by consequence the destruction of the Greek empire, was owing. Eleven hundred years and more had now elapsed since her foundation by Constantine. In the course of them, Goths, Huns, Avars, Persians, Bulgarians, Saracens, Russians, and indeed the Ottoman Turks themselves, had made their hostile assaults, or laid siege against it. But the fortifications were impregnable by them. Constantinople survived, <em>and with it the Greek empire</em>. Hence the anxiety of the Sultan Mahomet to find that which would remove the obstacle. ‘Canst thou cast a cannon,’ was his question to the founder of cannon that deserted to him, ‘of size sufficient to batter down the wall of Constantinople?’ Then the foundry was established at Adrianople, the cannon cast, the artillery prepared, and the siege began.",
    "puborder": 1656,
    "bookCode": "DAR",
    "bookTitle": "Daniel and The Revelation"
  }
]
